{"users": [
{
  "localId": "0sAN13hy7kRxpsWauuMACAme8cB2",
  "lastSignedInAt": "1760320156804",
  "createdAt": "1760320156804"
},
{
  "localId": "1ebXYJro88eTeUcSwUtqnGynD2k1",
  "lastSignedInAt": "1759919122809",
  "createdAt": "1759919122809"
},
{
  "localId": "2C8NpbHodXPOIIw5MdHwhydXhZ33",
  "lastSignedInAt": "1758707302968",
  "createdAt": "1758707302968"
},
{
  "localId": "5JRU4fZorhbnSYkVbb7itO3ghUu1",
  "lastSignedInAt": "1760749284633",
  "createdAt": "1760749284633"
},
{
  "localId": "6rWVMTAe0qd87v9CHCyM4I70za02",
  "lastSignedInAt": "1760317952658",
  "createdAt": "1760317952658"
},
{
  "localId": "Equnec8NZrNjjn8vntkTjorUlkz1",
  "lastSignedInAt": "1759979927751",
  "createdAt": "1759979927751"
},
{
  "localId": "FWPEJg7IpreA7I9kBDXvXcbMv8c2",
  "lastSignedInAt": "1760265946489",
  "createdAt": "1760265946489"
},
{
  "localId": "G9VAFSoWb2e2c9tzsrqYGvUYIlm2",
  "lastSignedInAt": "1757916238670",
  "createdAt": "1757916238670"
},
{
  "localId": "HAVOksumeVVCNXuQfhdadLnnfnJ3",
  "lastSignedInAt": "1757917059186",
  "createdAt": "1757917059186"
},
{
  "localId": "HFTArWjhNOYT8h5STgG743GMZfH3",
  "lastSignedInAt": "1759993597513",
  "createdAt": "1759993597513"
},
{
  "localId": "IeVJFsxCsWd5Hh3PXjh7BSKidEo1",
  "lastSignedInAt": "1759993531162",
  "createdAt": "1759993531162"
},
{
  "localId": "JT4NeUL5EIR42E4GIcu1h2TirP72",
  "lastSignedInAt": "1759398275537",
  "createdAt": "1759398275537"
},
{
  "localId": "OTQJzFwGIuUNGBIcegpaPetg1dI3",
  "lastSignedInAt": "1759395498034",
  "createdAt": "1759395498034"
},
{
  "localId": "QzlBgkQDblhWn3EY0AuKP4EGiRT2",
  "lastSignedInAt": "1759571898327",
  "createdAt": "1759571898327"
},
{
  "localId": "Sm22JL02ezR6CwYhZFbnljZH8MN2",
  "lastSignedInAt": "1760456463887",
  "createdAt": "1760456463887"
},
{
  "localId": "Sn4Hrle3wSZ4DeWAaGrDQYcgrbP2",
  "displayName": "Test",
  "lastSignedInAt": "1759402609004",
  "createdAt": "1759402609004"
},
{
  "localId": "THcrCHrF3ORbfx49Jt0aZysqnI72",
  "lastSignedInAt": "1759830794833",
  "createdAt": "1759830794833"
},
{
  "localId": "TVSIkPNQYySKTlrtxZ7wUTf2R743",
  "lastSignedInAt": "1760347517711",
  "createdAt": "1760347517711"
},
{
  "localId": "VWb4632ohzdAEP1fDzfGjqyEoL03",
  "lastSignedInAt": "1760318111576",
  "createdAt": "1760318111576"
},
{
  "localId": "WlvHqZ5olcTnRGryZdZMGWZv7s63",
  "lastSignedInAt": "1760318211698",
  "createdAt": "1760318211698"
},
{
  "localId": "XpHq3HwrwiQx5bFwmVAXRBrRVS73",
  "lastSignedInAt": "1758718598284",
  "createdAt": "1758718598284"
},
{
  "localId": "YAZfahx0ukXih7cWFLDC3DTJUkb2",
  "lastSignedInAt": "1759569168655",
  "createdAt": "1759569168655"
},
{
  "localId": "a56c8xZ73jVqeGcM8UDSGnjEAVD2",
  "lastSignedInAt": "1760326593397",
  "createdAt": "1760326593397"
},
{
  "localId": "cslYhFRFCsQ3D0c3R871yYXpvjx1",
  "lastSignedInAt": "1759993655965",
  "createdAt": "1759993655965"
},
{
  "localId": "dlEGdL4yLpZFizyIKutuH2paatO2",
  "lastSignedInAt": "1759569164963",
  "createdAt": "1759569164963"
},
{
  "localId": "eYb53RwQOFOC5RXISqYL2jrr2Pe2",
  "lastSignedInAt": "1758718864360",
  "createdAt": "1758718864360"
},
{
  "localId": "fmn0OMNMaSWBN3ly5HE1Vmj3MMZ2",
  "displayName": "Coy Jacobs",
  "lastSignedInAt": "1760318226198",
  "createdAt": "1760318226198"
},
{
  "localId": "gbAZOqe9qgTiDKssBmmuerowFPH2",
  "lastSignedInAt": "1760318439811",
  "createdAt": "1760318439811"
},
{
  "localId": "hgWht929Tneo8IhAQsplpK7GM9w2",
  "lastSignedInAt": "1758718448802",
  "createdAt": "1758718448802"
},
{
  "localId": "jTyEcynMYscVhV4VeQhUf0QCVY02",
  "lastSignedInAt": "1760339040772",
  "createdAt": "1760339040772"
},
{
  "localId": "lEItGIkwvQVw2KHpUcGt5lI9Jx73",
  "lastSignedInAt": "1759572599430",
  "createdAt": "1759572599430"
},
{
  "localId": "p3ZanAbqYpSab8HGFbbtoJ3zrU62",
  "lastSignedInAt": "1759573010743",
  "createdAt": "1759573010743"
},
{
  "localId": "pEMsVWAtGKbFWh7Z8H7yWmVlV1g1",
  "email": "coyjacobs@mtaftlogging.com",
  "emailVerified": false,
  "passwordHash": "L674XNeNW3DwEu1gCueozDailKSELXz86Bjlr2ijFG+CRf2cSnPxorlweYTJKlekgX7jLIgUAoPE9oSEa7LWWg==",
  "salt": "HuPy95EJ5pLIzQ==",
  "displayName": "Coy jacobs",
  "lastSignedInAt": "1760861894072",
  "createdAt": "1760686761938",
  "disabled": false,
  "providerUserInfo": []
},
{
  "localId": "rbiIc8UPGcSW5vUGvkqigD5mTHi1",
  "lastSignedInAt": "1759119562734",
  "createdAt": "1759119562734"
},
{
  "localId": "wcimE5fTVlRXDPaUX0bfltAFmyL2",
  "lastSignedInAt": "1760321967136",
  "createdAt": "1760321967136"
},
{
  "localId": "wnJ9pawVBKVLBrOm2nh0lkqUgDg1",
  "lastSignedInAt": "1759395945510",
  "createdAt": "1759395945510"
},
{
  "localId": "xQXrzxpe1zVDhVvS4mlVHSbRCaI2",
  "lastSignedInAt": "1760265072008",
  "createdAt": "1760265072008"
},
{
  "localId": "z5KKSTxOJifELBB3byWxEuFlyHu2",
  "displayName": "Coy Jacobs",
  "lastSignedInAt": "1760319515032",
  "createdAt": "1760319515032"
},
{
  "localId": "z6wFugld5QMPU66idBUIz0sBH4y2",
  "lastSignedInAt": "1760749011955",
  "createdAt": "1760749011955"
}]}